SmileyDB3/SmileyDB3.py
SmileyDB3/__init__.py
SmileyDB3-0.3.7.2.dist-info/LICENSE
SmileyDB3-0.3.7.2.dist-info/METADATA
SmileyDB3-0.3.7.2.dist-info/WHEEL
SmileyDB3-0.3.7.2.dist-info/top_level.txt
SmileyDB3-0.3.7.2.dist-info/RECORD
