Metadata-Version: 2.1
Name: SmileyDB3
Version: 0.3.7.2
Summary: SmileyDB3 is a library built on sqlite3 to make working with databases easier
Home-page: https://github.com/amr2018/SmileyDB3
Author: Free Python Code
Author-email: amr.ee@yahoo.com
License: MIT
Classifier: License :: OSI Approved :: MIT License
Classifier: Programming Language :: Python
Classifier: Programming Language :: Python :: 3
Classifier: Programming Language :: Python :: 3.6
Classifier: Programming Language :: Python :: Implementation :: CPython
Classifier: Programming Language :: Python :: Implementation :: PyPy
Requires-Python: >=3.1.0
License-File: LICENSE
Requires-Dist: bcrypt
